mlsauce/__init__.py
mlsauce/_config.py
mlsauce/setup.py
mlsauce/adaopt/__init__.py
mlsauce/adaopt/_adaopt.py
mlsauce/adaopt/_adaoptc.c
mlsauce/adaopt/_adaoptc.cpython-311-darwin.so
mlsauce/adaopt/setup.py
mlsauce/booster/__init__.py
mlsauce/booster/_booster_classifier.py
mlsauce/booster/_booster_regressor.py
mlsauce/booster/_boosterc.c
mlsauce/booster/_boosterc.cpython-311-darwin.so
mlsauce/booster/setup.py
mlsauce/datasets/__init__.py
mlsauce/datasets/dowload.py
mlsauce/encoders/__init__.py
mlsauce/encoders/target_encoders.py
mlsauce/lasso/__init__.py
mlsauce/lasso/_lasso.py
mlsauce/lasso/_lassoc.c
mlsauce/lasso/_lassoc.cpython-311-darwin.so
mlsauce/lasso/setup.py
mlsauce/ridge/__init__.py
mlsauce/ridge/_ridge.py
mlsauce/ridge/_ridgec.c
mlsauce/ridge/_ridgec.cpython-311-darwin.so
mlsauce/ridge/setup.py
mlsauce/stump/__init__.py
mlsauce/stump/_stump_classifier.py
mlsauce/stump/_stumpc.c
mlsauce/stump/_stumpc.cpython-311-darwin.so
mlsauce/stump/setup.py
mlsauce/tests/__init__.py
mlsauce/tests/test_adaopt.py
mlsauce/utils/__init__.py
mlsauce/utils/memoryuse/__init__.py
mlsauce/utils/memoryuse/mem_usage.py
mlsauce/utils/misc/__init__.py
mlsauce/utils/misc/misc.py
mlsauce/utils/sampling/__init__.py
mlsauce/utils/sampling/rowsubsampling.py
mlsauce-0.10.7.dist-info/LICENSE
mlsauce-0.10.7.dist-info/METADATA
mlsauce-0.10.7.dist-info/WHEEL
mlsauce-0.10.7.dist-info/top_level.txt
mlsauce-0.10.7.dist-info/RECORD
